tap_geosource/__init__.py
tap_geosource/discovery.py
tap_geosource/geo.py
tap_geosource/sync.py
tap_geosource-0.1.0.dist-info/LICENSE
tap_geosource-0.1.0.dist-info/METADATA
tap_geosource-0.1.0.dist-info/WHEEL
tap_geosource-0.1.0.dist-info/entry_points.txt
tap_geosource-0.1.0.dist-info/top_level.txt
tap_geosource-0.1.0.dist-info/RECORD
